AUTHORS
CHANGES
LICENSE
MANIFEST.in
README.md
TODO
setup.py
artwork/screenshots/01.alltags.png
artwork/screenshots/02.tag.png
artwork/screenshots/03.addlink.png
strawberry/__init__.py
strawberry/link.py
strawberry/strawberry.py
strawberry/tag.py
strawberry.egg-info/PKG-INFO
strawberry.egg-info/SOURCES.txt
strawberry.egg-info/dependency_links.txt
strawberry.egg-info/requires.txt
strawberry.egg-info/top_level.txt
strawberry/templates/404.html
strawberry/templates/addoredit.html
strawberry/templates/base.html
strawberry/templates/index.html
strawberry/templates/tag.html
strawberry/templates/styles/default/jquery-1.5.1.js
strawberry/templates/styles/default/jquery-1.5.1.min.js
strawberry/templates/styles/default/jquery.js
strawberry/templates/styles/default/style.css
strawberry/templates/styles/default/ressources/add.png
strawberry/templates/styles/default/ressources/edit.png
strawberry/templates/styles/default/ressources/favicon.png
strawberry/templates/styles/default/ressources/loading.gif
strawberry/templates/styles/default/ressources/strawberry_icon.png
strawberry/templates/styles/default/ressources/strawberry_icon_old.png
strawberry/templates/styles/default/ressources/warning.png